<?xml version="1.0" encoding="utf-8" ?>
<dwsync>
<file name="effects.core.js" server="C:/wamp/www/tretra7/" local="130308277080000000" remote="130308277080000000" Dst="2" />
<file name="effects.highlight.js" server="C:/wamp/www/tretra7/" local="130308277070000000" remote="130308277070000000" Dst="2" />
<file name="jquery-1.5.1.min.js" server="C:/wamp/www/tretra7/" local="130308277060000000" remote="130308277060000000" Dst="2" />
<file name="jquery-ui-1.8.14.custom.css" server="C:/wamp/www/tretra7/" local="130308277070000000" remote="130308277070000000" Dst="2" />
<file name="jquery.ui.core.min.js" server="C:/wamp/www/tretra7/" local="130308277080000000" remote="130308277080000000" Dst="2" />
<file name="jquery.ui.position.min.js" server="C:/wamp/www/tretra7/" local="130308277070000000" remote="130308277070000000" Dst="2" />
<file name="jquery.ui.tabs.min.js" server="C:/wamp/www/tretra7/" local="130308277070000000" remote="130308277070000000" Dst="2" />
<file name="jquery.ui.widget.min.js" server="C:/wamp/www/tretra7/" local="130308277070000000" remote="130308277070000000" Dst="2" />
<file name="ui.accordion.js" server="C:/wamp/www/tretra7/" local="130308277050000000" remote="130308277050000000" Dst="2" />
<file name="ui.core.js" server="C:/wamp/www/tretra7/" local="130308277060000000" remote="130308277060000000" Dst="2" />
<file name="ui.css" server="C:/wamp/www/tretra7/" local="130308277070000000" remote="130308277070000000" Dst="2" />
<file name="ui.datepicker.js" server="C:/wamp/www/tretra7/" local="130308277060000000" remote="130308277060000000" Dst="2" />
<file name="ui.dialog.js" server="C:/wamp/www/tretra7/" local="130308277050000000" remote="130308277050000000" Dst="2" />
<file name="ui.draggable.js" server="C:/wamp/www/tretra7/" local="130308277060000000" remote="130308277060000000" Dst="2" />
<file name="ui.droppable.js" server="C:/wamp/www/tretra7/" local="130308277070000000" remote="130308277070000000" Dst="2" />
<file name="ui.js" server="C:/wamp/www/tretra7/" local="130308277070000000" remote="130308277070000000" Dst="2" />
<file name="ui.progressbar.js" server="C:/wamp/www/tretra7/" local="130308277050000000" remote="130308277050000000" Dst="2" />
<file name="ui.resizable.js" server="C:/wamp/www/tretra7/" local="130308277050000000" remote="130308277050000000" Dst="2" />
<file name="ui.slider.js" server="C:/wamp/www/tretra7/" local="130308277080000000" remote="130308277080000000" Dst="2" />
<file name="ui.sortable.js" server="C:/wamp/www/tretra7/" local="130308277080000000" remote="130308277080000000" Dst="2" />
<file name="ui.tabs.js" server="C:/wamp/www/tretra7/" local="130308277070000000" remote="130308277070000000" Dst="2" />
<file name="ui.timepicker.js" server="C:/wamp/www/tretra7/" local="130308277080000000" remote="130308277080000000" Dst="2" />
<file name="effects.core.js" server="ftp.terra-mar.info//tretra7.1/" local="130308277085576577" remote="130317125400000000" Dst="1" />
<file name="effects.highlight.js" server="ftp.terra-mar.info//tretra7.1/" local="130308277074496563" remote="130317125400000000" Dst="1" />
<file name="jquery-ui-1.8.14.custom.css" server="ftp.terra-mar.info//tretra7.1/" local="130308277073475688" remote="130317125400000000" Dst="1" />
<file name="jquery-1.5.1.min.js" server="ftp.terra-mar.info//tretra7.1/" local="130308277068020713" remote="130317125400000000" Dst="1" />
<file name="jquery.ui.core.min.js" server="ftp.terra-mar.info//tretra7.1/" local="130308277080582074" remote="130317125400000000" Dst="1" />
<file name="jquery.ui.position.min.js" server="ftp.terra-mar.info//tretra7.1/" local="130308277076898738" remote="130317125400000000" Dst="1" />
<file name="jquery.ui.tabs.min.js" server="ftp.terra-mar.info//tretra7.1/" local="130308277075007063" remote="130317125400000000" Dst="1" />
<file name="jquery.ui.widget.min.js" server="ftp.terra-mar.info//tretra7.1/" local="130308277070623068" remote="130317125400000000" Dst="1" />
<file name="ui.accordion.js" server="ftp.terra-mar.info//tretra7.1/" local="130308277059342920" remote="130317125400000000" Dst="1" />
<file name="ui.core.js" server="ftp.terra-mar.info//tretra7.1/" local="130308277061404941" remote="130317125400000000" Dst="1" />
<file name="ui.css" server="ftp.terra-mar.info//tretra7.1/" local="130308277077809603" remote="130317125400000000" Dst="1" />
<file name="ui.dialog.js" server="ftp.terra-mar.info//tretra7.1/" local="130308277053268000" remote="130317126000000000" Dst="1" />
<file name="ui.datepicker.js" server="ftp.terra-mar.info//tretra7.1/" local="130308277062936162" remote="130317126000000000" Dst="1" />
<file name="ui.droppable.js" server="ftp.terra-mar.info//tretra7.1/" local="130308277070903321" remote="130317126000000000" Dst="1" />
<file name="ui.draggable.js" server="ftp.terra-mar.info//tretra7.1/" local="130308277066599476" remote="130317126000000000" Dst="1" />
<file name="ui.progressbar.js" server="ftp.terra-mar.info//tretra7.1/" local="130308277053887992" remote="130317126000000000" Dst="1" />
<file name="ui.js" server="ftp.terra-mar.info//tretra7.1/" local="130308277073425600" remote="130317126000000000" Dst="1" />
<file name="ui.resizable.js" server="ftp.terra-mar.info//tretra7.1/" local="130308277058371996" remote="130317126000000000" Dst="1" />
<file name="ui.slider.js" server="ftp.terra-mar.info//tretra7.1/" local="130308277081963309" remote="130317126000000000" Dst="1" />
<file name="ui.sortable.js" server="ftp.terra-mar.info//tretra7.1/" local="130308277081022502" remote="130317126000000000" Dst="1" />
<file name="ui.tabs.js" server="ftp.terra-mar.info//tretra7.1/" local="130308277071653995" remote="130317126000000000" Dst="1" />
<file name="ui.timepicker.js" server="ftp.terra-mar.info//tretra7.1/" local="130308277083785575" remote="130317126000000000" Dst="1" />
<file name="effects.highlight.js" server="ftp.terra-mar.info//tretra7.2/" local="130308277070000000" remote="130318472400000000" Dst="1" />
<file name="ui.datepicker.js" server="ftp.terra-mar.info//tretra7.2/" local="130308277060000000" remote="130318472400000000" Dst="1" />
<file name="effects.core.js" server="C:/wamp/www/tretra_v2/" local="130308277080000000" remote="130308277080000000" Dst="2" />
<file name="effects.highlight.js" server="C:/wamp/www/tretra_v2/" local="130308277070000000" remote="130308277070000000" Dst="2" />
<file name="jquery-1.5.1.min.js" server="C:/wamp/www/tretra_v2/" local="130308277060000000" remote="130308277060000000" Dst="2" />
<file name="jquery-ui-1.8.14.custom.css" server="C:/wamp/www/tretra_v2/" local="130308277070000000" remote="130308277070000000" Dst="2" />
<file name="jquery.ui.core.min.js" server="C:/wamp/www/tretra_v2/" local="130308277080000000" remote="130308277080000000" Dst="2" />
<file name="jquery.ui.position.min.js" server="C:/wamp/www/tretra_v2/" local="130308277070000000" remote="130308277070000000" Dst="2" />
<file name="jquery.ui.tabs.min.js" server="C:/wamp/www/tretra_v2/" local="130308277070000000" remote="130308277070000000" Dst="2" />
<file name="jquery.ui.widget.min.js" server="C:/wamp/www/tretra_v2/" local="130308277070000000" remote="130308277070000000" Dst="2" />
<file name="ui.accordion.js" server="C:/wamp/www/tretra_v2/" local="130308277050000000" remote="130308277050000000" Dst="2" />
<file name="ui.core.js" server="C:/wamp/www/tretra_v2/" local="130308277060000000" remote="130308277060000000" Dst="2" />
<file name="ui.css" server="C:/wamp/www/tretra_v2/" local="130308277070000000" remote="130308277070000000" Dst="2" />
<file name="ui.datepicker.js" server="C:/wamp/www/tretra_v2/" local="130308277060000000" remote="130308277060000000" Dst="2" />
<file name="ui.dialog.js" server="C:/wamp/www/tretra_v2/" local="130308277050000000" remote="130308277050000000" Dst="2" />
<file name="ui.draggable.js" server="C:/wamp/www/tretra_v2/" local="130308277060000000" remote="130308277060000000" Dst="2" />
<file name="ui.droppable.js" server="C:/wamp/www/tretra_v2/" local="130308277070000000" remote="130308277070000000" Dst="2" />
<file name="ui.js" server="C:/wamp/www/tretra_v2/" local="130308277070000000" remote="130308277070000000" Dst="2" />
<file name="ui.progressbar.js" server="C:/wamp/www/tretra_v2/" local="130308277050000000" remote="130308277050000000" Dst="2" />
<file name="ui.resizable.js" server="C:/wamp/www/tretra_v2/" local="130308277050000000" remote="130308277050000000" Dst="2" />
<file name="ui.slider.js" server="C:/wamp/www/tretra_v2/" local="130308277080000000" remote="130308277080000000" Dst="2" />
<file name="ui.sortable.js" server="C:/wamp/www/tretra_v2/" local="130308277080000000" remote="130308277080000000" Dst="2" />
<file name="ui.tabs.js" server="C:/wamp/www/tretra_v2/" local="130308277070000000" remote="130308277070000000" Dst="2" />
<file name="ui.timepicker.js" server="C:/wamp/www/tretra_v2/" local="130308277080000000" remote="130308277080000000" Dst="2" />
<file name="effects.core.js" server="C:/wamp/www/tretra-v2/" local="130308277080000000" remote="130308277080000000" Dst="2" />
<file name="effects.highlight.js" server="C:/wamp/www/tretra-v2/" local="130308277070000000" remote="130308277070000000" Dst="2" />
<file name="jquery-1.5.1.min.js" server="C:/wamp/www/tretra-v2/" local="130308277060000000" remote="130308277060000000" Dst="2" />
<file name="jquery-ui-1.8.14.custom.css" server="C:/wamp/www/tretra-v2/" local="130308277070000000" remote="130308277070000000" Dst="2" />
<file name="jquery.ui.core.min.js" server="C:/wamp/www/tretra-v2/" local="130308277080000000" remote="130308277080000000" Dst="2" />
<file name="jquery.ui.position.min.js" server="C:/wamp/www/tretra-v2/" local="130308277070000000" remote="130308277070000000" Dst="2" />
<file name="jquery.ui.tabs.min.js" server="C:/wamp/www/tretra-v2/" local="130308277070000000" remote="130308277070000000" Dst="2" />
<file name="jquery.ui.widget.min.js" server="C:/wamp/www/tretra-v2/" local="130308277070000000" remote="130308277070000000" Dst="2" />
<file name="ui.accordion.js" server="C:/wamp/www/tretra-v2/" local="130308277050000000" remote="130308277050000000" Dst="2" />
<file name="ui.core.js" server="C:/wamp/www/tretra-v2/" local="130308277060000000" remote="130308277060000000" Dst="2" />
<file name="ui.css" server="C:/wamp/www/tretra-v2/" local="130308277070000000" remote="130308277070000000" Dst="2" />
<file name="ui.datepicker.js" server="C:/wamp/www/tretra-v2/" local="130308277060000000" remote="130308277060000000" Dst="2" />
<file name="ui.dialog.js" server="C:/wamp/www/tretra-v2/" local="130308277050000000" remote="130308277050000000" Dst="2" />
<file name="ui.draggable.js" server="C:/wamp/www/tretra-v2/" local="130308277060000000" remote="130308277060000000" Dst="2" />
<file name="ui.droppable.js" server="C:/wamp/www/tretra-v2/" local="130308277070000000" remote="130308277070000000" Dst="2" />
<file name="ui.js" server="C:/wamp/www/tretra-v2/" local="130308277070000000" remote="130308277070000000" Dst="2" />
<file name="ui.progressbar.js" server="C:/wamp/www/tretra-v2/" local="130308277050000000" remote="130308277050000000" Dst="2" />
<file name="ui.resizable.js" server="C:/wamp/www/tretra-v2/" local="130308277050000000" remote="130308277050000000" Dst="2" />
<file name="ui.slider.js" server="C:/wamp/www/tretra-v2/" local="130308277080000000" remote="130308277080000000" Dst="2" />
<file name="ui.sortable.js" server="C:/wamp/www/tretra-v2/" local="130308277080000000" remote="130308277080000000" Dst="2" />
<file name="ui.tabs.js" server="C:/wamp/www/tretra-v2/" local="130308277070000000" remote="130308277070000000" Dst="2" />
<file name="ui.timepicker.js" server="C:/wamp/www/tretra-v2/" local="130308277080000000" remote="130308277080000000" Dst="2" />
<file name="effects.core.js" server="C:/wamp/www/tretra_v12/" local="130308277080000000" remote="130308277080000000" Dst="2" />
<file name="effects.highlight.js" server="C:/wamp/www/tretra_v12/" local="130308277070000000" remote="130308277070000000" Dst="2" />
<file name="jquery-1.5.1.min.js" server="C:/wamp/www/tretra_v12/" local="130308277060000000" remote="130308277060000000" Dst="2" />
<file name="jquery-ui-1.8.14.custom.css" server="C:/wamp/www/tretra_v12/" local="130308277070000000" remote="130308277070000000" Dst="2" />
<file name="jquery.ui.core.min.js" server="C:/wamp/www/tretra_v12/" local="130308277080000000" remote="130308277080000000" Dst="2" />
<file name="jquery.ui.position.min.js" server="C:/wamp/www/tretra_v12/" local="130308277070000000" remote="130308277070000000" Dst="2" />
<file name="jquery.ui.tabs.min.js" server="C:/wamp/www/tretra_v12/" local="130308277070000000" remote="130308277070000000" Dst="2" />
<file name="jquery.ui.widget.min.js" server="C:/wamp/www/tretra_v12/" local="130308277070000000" remote="130308277070000000" Dst="2" />
<file name="ui.accordion.js" server="C:/wamp/www/tretra_v12/" local="130308277050000000" remote="130308277050000000" Dst="2" />
<file name="ui.core.js" server="C:/wamp/www/tretra_v12/" local="130308277060000000" remote="130308277060000000" Dst="2" />
<file name="ui.css" server="C:/wamp/www/tretra_v12/" local="130308277070000000" remote="130308277070000000" Dst="2" />
<file name="ui.datepicker.js" server="C:/wamp/www/tretra_v12/" local="130308277060000000" remote="130308277060000000" Dst="2" />
<file name="ui.dialog.js" server="C:/wamp/www/tretra_v12/" local="130308277050000000" remote="130308277050000000" Dst="2" />
<file name="ui.draggable.js" server="C:/wamp/www/tretra_v12/" local="130308277060000000" remote="130308277060000000" Dst="2" />
<file name="ui.droppable.js" server="C:/wamp/www/tretra_v12/" local="130308277070000000" remote="130308277070000000" Dst="2" />
<file name="ui.js" server="C:/wamp/www/tretra_v12/" local="130308277070000000" remote="130308277070000000" Dst="2" />
<file name="ui.progressbar.js" server="C:/wamp/www/tretra_v12/" local="130308277050000000" remote="130308277050000000" Dst="2" />
<file name="ui.resizable.js" server="C:/wamp/www/tretra_v12/" local="130308277050000000" remote="130308277050000000" Dst="2" />
<file name="ui.slider.js" server="C:/wamp/www/tretra_v12/" local="130308277080000000" remote="130308277080000000" Dst="2" />
<file name="ui.sortable.js" server="C:/wamp/www/tretra_v12/" local="130308277080000000" remote="130308277080000000" Dst="2" />
<file name="ui.tabs.js" server="C:/wamp/www/tretra_v12/" local="130308277070000000" remote="130308277070000000" Dst="2" />
<file name="ui.timepicker.js" server="C:/wamp/www/tretra_v12/" local="130308277080000000" remote="130308277080000000" Dst="2" />
<file name="effects.core.js" server="192.241.211.13//var/www/html/tretra_v2/" local="130308277080000000" remote="130980767480000000" Dst="1" />
<file name="effects.highlight.js" server="192.241.211.13//var/www/html/tretra_v2/" local="130308277070000000" remote="130980767490000000" Dst="1" />
<file name="jquery-1.5.1.min.js" server="192.241.211.13//var/www/html/tretra_v2/" local="130308277060000000" remote="130980767490000000" Dst="1" />
<file name="jquery-ui-1.8.14.custom.css" server="192.241.211.13//var/www/html/tretra_v2/" local="130308277070000000" remote="130980767490000000" Dst="1" />
<file name="jquery.ui.core.min.js" server="192.241.211.13//var/www/html/tretra_v2/" local="130308277080000000" remote="130980767500000000" Dst="1" />
<file name="jquery.ui.position.min.js" server="192.241.211.13//var/www/html/tretra_v2/" local="130308277070000000" remote="130980767500000000" Dst="1" />
<file name="jquery.ui.tabs.min.js" server="192.241.211.13//var/www/html/tretra_v2/" local="130308277070000000" remote="130980767500000000" Dst="1" />
<file name="jquery.ui.widget.min.js" server="192.241.211.13//var/www/html/tretra_v2/" local="130308277070000000" remote="130980767500000000" Dst="1" />
<file name="ui.accordion.js" server="192.241.211.13//var/www/html/tretra_v2/" local="130308277050000000" remote="130980767500000000" Dst="1" />
<file name="ui.core.js" server="192.241.211.13//var/www/html/tretra_v2/" local="130308277060000000" remote="130980767510000000" Dst="1" />
<file name="ui.css" server="192.241.211.13//var/www/html/tretra_v2/" local="130308277070000000" remote="130980767510000000" Dst="1" />
<file name="ui.datepicker.js" server="192.241.211.13//var/www/html/tretra_v2/" local="130308277060000000" remote="130980767510000000" Dst="1" />
<file name="ui.dialog.js" server="192.241.211.13//var/www/html/tretra_v2/" local="130308277050000000" remote="130980767520000000" Dst="1" />
<file name="ui.draggable.js" server="192.241.211.13//var/www/html/tretra_v2/" local="130308277060000000" remote="130980767520000000" Dst="1" />
<file name="ui.droppable.js" server="192.241.211.13//var/www/html/tretra_v2/" local="130308277070000000" remote="130980767520000000" Dst="1" />
<file name="ui.js" server="192.241.211.13//var/www/html/tretra_v2/" local="130308277070000000" remote="130980767520000000" Dst="1" />
<file name="ui.progressbar.js" server="192.241.211.13//var/www/html/tretra_v2/" local="130308277050000000" remote="130980767520000000" Dst="1" />
<file name="ui.resizable.js" server="192.241.211.13//var/www/html/tretra_v2/" local="130308277050000000" remote="130980767520000000" Dst="1" />
<file name="ui.slider.js" server="192.241.211.13//var/www/html/tretra_v2/" local="130308277080000000" remote="130980767530000000" Dst="1" />
<file name="ui.sortable.js" server="192.241.211.13//var/www/html/tretra_v2/" local="130308277080000000" remote="130980767530000000" Dst="1" />
<file name="ui.tabs.js" server="192.241.211.13//var/www/html/tretra_v2/" local="130308277070000000" remote="130980767530000000" Dst="1" />
<file name="ui.timepicker.js" server="192.241.211.13//var/www/html/tretra_v2/" local="130308277080000000" remote="130980767530000000" Dst="1" />
<file name="effects.core.js" server="104.236.178.96//var/www/sunnydays.me/public_html/" local="130308277080000000" remote="130991038870000000" Dst="1" />
<file name="effects.highlight.js" server="104.236.178.96//var/www/sunnydays.me/public_html/" local="130308277070000000" remote="130991038870000000" Dst="1" />
<file name="jquery-1.5.1.min.js" server="104.236.178.96//var/www/sunnydays.me/public_html/" local="130308277060000000" remote="130991038880000000" Dst="1" />
<file name="jquery-ui-1.8.14.custom.css" server="104.236.178.96//var/www/sunnydays.me/public_html/" local="130308277070000000" remote="130991038880000000" Dst="1" />
<file name="jquery.ui.core.min.js" server="104.236.178.96//var/www/sunnydays.me/public_html/" local="130308277080000000" remote="130991038890000000" Dst="1" />
<file name="jquery.ui.position.min.js" server="104.236.178.96//var/www/sunnydays.me/public_html/" local="130308277070000000" remote="130991038900000000" Dst="1" />
<file name="jquery.ui.tabs.min.js" server="104.236.178.96//var/www/sunnydays.me/public_html/" local="130308277070000000" remote="130991038900000000" Dst="1" />
<file name="jquery.ui.widget.min.js" server="104.236.178.96//var/www/sunnydays.me/public_html/" local="130308277070000000" remote="130991038900000000" Dst="1" />
<file name="ui.accordion.js" server="104.236.178.96//var/www/sunnydays.me/public_html/" local="130308277050000000" remote="130991038900000000" Dst="1" />
<file name="ui.core.js" server="104.236.178.96//var/www/sunnydays.me/public_html/" local="130308277060000000" remote="130991038920000000" Dst="1" />
<file name="ui.css" server="104.236.178.96//var/www/sunnydays.me/public_html/" local="130308277070000000" remote="130991038940000000" Dst="1" />
<file name="ui.datepicker.js" server="104.236.178.96//var/www/sunnydays.me/public_html/" local="130308277060000000" remote="130991038960000000" Dst="1" />
<file name="ui.dialog.js" server="104.236.178.96//var/www/sunnydays.me/public_html/" local="130308277050000000" remote="130991038970000000" Dst="1" />
<file name="ui.draggable.js" server="104.236.178.96//var/www/sunnydays.me/public_html/" local="130308277060000000" remote="130991038990000000" Dst="1" />
<file name="ui.droppable.js" server="104.236.178.96//var/www/sunnydays.me/public_html/" local="130308277070000000" remote="130991038990000000" Dst="1" />
<file name="ui.js" server="104.236.178.96//var/www/sunnydays.me/public_html/" local="130308277070000000" remote="130991038990000000" Dst="1" />
<file name="ui.progressbar.js" server="104.236.178.96//var/www/sunnydays.me/public_html/" local="130308277050000000" remote="130991039000000000" Dst="1" />
<file name="ui.resizable.js" server="104.236.178.96//var/www/sunnydays.me/public_html/" local="130308277050000000" remote="130991039000000000" Dst="1" />
<file name="ui.slider.js" server="104.236.178.96//var/www/sunnydays.me/public_html/" local="130308277080000000" remote="130991039010000000" Dst="1" />
<file name="ui.sortable.js" server="104.236.178.96//var/www/sunnydays.me/public_html/" local="130308277080000000" remote="130991039010000000" Dst="1" />
<file name="ui.tabs.js" server="104.236.178.96//var/www/sunnydays.me/public_html/" local="130308277070000000" remote="130991039010000000" Dst="1" />
<file name="ui.timepicker.js" server="104.236.178.96//var/www/sunnydays.me/public_html/" local="130308277080000000" remote="130991039020000000" Dst="1" />
<file name="ui.timepicker.js" server="104.236.178.96//" local="130308277080000000" remote="130993474460000000" Dst="1" />
<file name="ui.tabs.js" server="104.236.178.96//" local="130308277070000000" remote="130993474470000000" Dst="1" />
<file name="ui.sortable.js" server="104.236.178.96//" local="130308277080000000" remote="130993474470000000" Dst="1" />
<file name="ui.slider.js" server="104.236.178.96//" local="130308277080000000" remote="130993474470000000" Dst="1" />
<file name="ui.resizable.js" server="104.236.178.96//" local="130308277050000000" remote="130993474480000000" Dst="1" />
<file name="ui.progressbar.js" server="104.236.178.96//" local="130308277050000000" remote="130993474480000000" Dst="1" />
<file name="ui.js" server="104.236.178.96//" local="130308277070000000" remote="130993474480000000" Dst="1" />
<file name="ui.droppable.js" server="104.236.178.96//" local="130308277070000000" remote="130993474480000000" Dst="1" />
<file name="ui.draggable.js" server="104.236.178.96//" local="130308277060000000" remote="130993474490000000" Dst="1" />
<file name="ui.dialog.js" server="104.236.178.96//" local="130308277050000000" remote="130993474490000000" Dst="1" />
<file name="ui.datepicker.js" server="104.236.178.96//" local="130308277060000000" remote="130993474490000000" Dst="1" />
<file name="ui.css" server="104.236.178.96//" local="130308277070000000" remote="130993474500000000" Dst="1" />
<file name="ui.core.js" server="104.236.178.96//" local="130308277060000000" remote="130993474500000000" Dst="1" />
<file name="ui.accordion.js" server="104.236.178.96//" local="130308277050000000" remote="130993474500000000" Dst="1" />
<file name="jquery.ui.widget.min.js" server="104.236.178.96//" local="130308277070000000" remote="130993474500000000" Dst="1" />
<file name="jquery.ui.tabs.min.js" server="104.236.178.96//" local="130308277070000000" remote="130993474510000000" Dst="1" />
<file name="jquery.ui.position.min.js" server="104.236.178.96//" local="130308277070000000" remote="130993474510000000" Dst="1" />
<file name="jquery.ui.core.min.js" server="104.236.178.96//" local="130308277080000000" remote="130993474520000000" Dst="1" />
<file name="jquery-ui-1.8.14.custom.css" server="104.236.178.96//" local="130308277070000000" remote="130993474520000000" Dst="1" />
<file name="jquery-1.5.1.min.js" server="104.236.178.96//" local="130308277060000000" remote="130993474520000000" Dst="1" />
<file name="effects.highlight.js" server="104.236.178.96//" local="130308277070000000" remote="130993474520000000" Dst="1" />
<file name="effects.core.js" server="104.236.178.96//" local="130308277080000000" remote="130993474530000000" Dst="1" />
<file name="effects.core.js" server="45.55.23.123//var/www/sunnydays.me/public_html/" local="130308277080000000" remote="131003119060000000" Dst="1" />
<file name="effects.highlight.js" server="45.55.23.123//var/www/sunnydays.me/public_html/" local="130308277070000000" remote="131003119060000000" Dst="1" />
<file name="jquery-1.5.1.min.js" server="45.55.23.123//var/www/sunnydays.me/public_html/" local="130308277060000000" remote="131003119060000000" Dst="1" />
<file name="jquery-ui-1.8.14.custom.css" server="45.55.23.123//var/www/sunnydays.me/public_html/" local="130308277070000000" remote="131003119060000000" Dst="1" />
<file name="jquery.ui.core.min.js" server="45.55.23.123//var/www/sunnydays.me/public_html/" local="130308277080000000" remote="131003119060000000" Dst="1" />
<file name="jquery.ui.position.min.js" server="45.55.23.123//var/www/sunnydays.me/public_html/" local="130308277070000000" remote="131003119060000000" Dst="1" />
<file name="jquery.ui.tabs.min.js" server="45.55.23.123//var/www/sunnydays.me/public_html/" local="130308277070000000" remote="131003119060000000" Dst="1" />
<file name="jquery.ui.widget.min.js" server="45.55.23.123//var/www/sunnydays.me/public_html/" local="130308277070000000" remote="131003119060000000" Dst="1" />
<file name="ui.accordion.js" server="45.55.23.123//var/www/sunnydays.me/public_html/" local="130308277050000000" remote="131003119060000000" Dst="1" />
<file name="ui.core.js" server="45.55.23.123//var/www/sunnydays.me/public_html/" local="130308277060000000" remote="131003119060000000" Dst="1" />
<file name="ui.css" server="45.55.23.123//var/www/sunnydays.me/public_html/" local="130308277070000000" remote="131003119070000000" Dst="1" />
<file name="ui.datepicker.js" server="45.55.23.123//var/www/sunnydays.me/public_html/" local="130308277060000000" remote="131003119070000000" Dst="1" />
<file name="ui.dialog.js" server="45.55.23.123//var/www/sunnydays.me/public_html/" local="130308277050000000" remote="131003119070000000" Dst="1" />
<file name="ui.draggable.js" server="45.55.23.123//var/www/sunnydays.me/public_html/" local="130308277060000000" remote="131003119070000000" Dst="1" />
<file name="ui.droppable.js" server="45.55.23.123//var/www/sunnydays.me/public_html/" local="130308277070000000" remote="131003119070000000" Dst="1" />
<file name="ui.js" server="45.55.23.123//var/www/sunnydays.me/public_html/" local="130308277070000000" remote="131003119070000000" Dst="1" />
<file name="ui.progressbar.js" server="45.55.23.123//var/www/sunnydays.me/public_html/" local="130308277050000000" remote="131003119070000000" Dst="1" />
<file name="ui.resizable.js" server="45.55.23.123//var/www/sunnydays.me/public_html/" local="130308277050000000" remote="131003119070000000" Dst="1" />
<file name="ui.slider.js" server="45.55.23.123//var/www/sunnydays.me/public_html/" local="130308277080000000" remote="131003119070000000" Dst="1" />
<file name="ui.sortable.js" server="45.55.23.123//var/www/sunnydays.me/public_html/" local="130308277080000000" remote="131003119080000000" Dst="1" />
<file name="ui.tabs.js" server="45.55.23.123//var/www/sunnydays.me/public_html/" local="130308277070000000" remote="131003119080000000" Dst="1" />
<file name="ui.timepicker.js" server="45.55.23.123//var/www/sunnydays.me/public_html/" local="130308277080000000" remote="131003119080000000" Dst="1" />
</dwsync>