<?xml version="1.0" encoding="utf-8" ?>
<dwsync>
<file name="BPRTT1.jpg" server="C:/wamp/www/tretra_v12/" local="130880470829157210" remote="130880470820000000" Dst="2" />
<file name="BPRTT2.jpg" server="C:/wamp/www/tretra_v12/" local="130880470829782884" remote="130880470820000000" Dst="2" />
<file name="BPRTT3.jpg" server="C:/wamp/www/tretra_v12/" local="130880470830624873" remote="130880470830000000" Dst="2" />
<file name="BPRTT4.jpg" server="C:/wamp/www/tretra_v12/" local="130880470831095187" remote="130880470830000000" Dst="2" />
<file name="BPRTT5.jpg" server="C:/wamp/www/tretra_v12/" local="130880470831515528" remote="130880470830000000" Dst="2" />
<file name="BPRTT1.jpg" server="192.241.211.13//var/www/html/tretra_v2/" local="130880470820000000" remote="130980761130000000" Dst="1" />
<file name="BPRTT2.jpg" server="192.241.211.13//var/www/html/tretra_v2/" local="130880470820000000" remote="130980761140000000" Dst="1" />
<file name="BPRTT3.jpg" server="192.241.211.13//var/www/html/tretra_v2/" local="130880470830000000" remote="130980761140000000" Dst="1" />
<file name="BPRTT4.jpg" server="192.241.211.13//var/www/html/tretra_v2/" local="130880470830000000" remote="130980761140000000" Dst="1" />
<file name="BPRTT5.jpg" server="192.241.211.13//var/www/html/tretra_v2/" local="130880470830000000" remote="130980761150000000" Dst="1" />
<file name="BPRTT1.jpg" server="104.236.178.96//var/www/sunnydays.me/public_html/" local="130880470820000000" remote="130991023810000000" Dst="1" />
<file name="BPRTT2.jpg" server="104.236.178.96//var/www/sunnydays.me/public_html/" local="130880470820000000" remote="130991023830000000" Dst="1" />
<file name="BPRTT3.jpg" server="104.236.178.96//var/www/sunnydays.me/public_html/" local="130880470830000000" remote="130991023830000000" Dst="1" />
<file name="BPRTT4.jpg" server="104.236.178.96//var/www/sunnydays.me/public_html/" local="130880470830000000" remote="130991023840000000" Dst="1" />
<file name="BPRTT5.jpg" server="104.236.178.96//var/www/sunnydays.me/public_html/" local="130880470830000000" remote="130991023850000000" Dst="1" />
<file name="BPRTT1.jpg" server="45.55.23.123//var/www/sunnydays.me/public_html/" local="130880470820000000" remote="131003114750000000" Dst="1" />
<file name="BPRTT2.jpg" server="45.55.23.123//var/www/sunnydays.me/public_html/" local="130880470820000000" remote="131003114760000000" Dst="1" />
<file name="BPRTT3.jpg" server="45.55.23.123//var/www/sunnydays.me/public_html/" local="130880470830000000" remote="131003114760000000" Dst="1" />
<file name="BPRTT4.jpg" server="45.55.23.123//var/www/sunnydays.me/public_html/" local="130880470830000000" remote="131003114760000000" Dst="1" />
<file name="BPRTT5.jpg" server="45.55.23.123//var/www/sunnydays.me/public_html/" local="130880470830000000" remote="131003114760000000" Dst="1" />
</dwsync>